carbone_sdk/__init__.py
carbone_sdk/carbone_sdk.py
carbone_sdk-1.1.1.dist-info/licenses/LICENSE.txt
carbone_sdk-1.1.1.dist-info/METADATA
carbone_sdk-1.1.1.dist-info/WHEEL
carbone_sdk-1.1.1.dist-info/top_level.txt
carbone_sdk-1.1.1.dist-info/RECORD
