Metadata-Version: 2.4
Name: carbone-sdk
Version: 1.1.1
Summary: Carbone API Python SDK to generate documents (PDF DOCX XLSX PPTX CSV XML HTML ODS ODT and more) from a JSON and a template.
Home-page: https://github.com/carboneio/carbone-sdk-python
Author: CarboneIO
Author-email: support@carbone.io
License: Apache-2.0
Classifier: Programming Language :: Python :: 3
Classifier: Operating System :: OS Independent
Classifier: Intended Audience :: Developers
Classifier: Development Status :: 5 - Production/Stable
Classifier: Topic :: Software Development :: Libraries :: Python Modules
Requires-Python: >=3.6
License-File: LICENSE.txt
Requires-Dist: requests
Dynamic: author
Dynamic: author-email
Dynamic: classifier
Dynamic: description
Dynamic: description-content-type
Dynamic: home-page
Dynamic: license
Dynamic: license-file
Dynamic: requires-dist
Dynamic: requires-python
Dynamic: summary
